{
    "section": "Quiz: Threshold Signatures Fundamentals",
    "questions": [
        {
            "type": "multiple_choice",
            "question": "In a (4, 7) threshold signature system, what is the minimum number of nodes required to create a valid signature?",
            "options": [
                "3 nodes",
                "4 nodes",
                "5 nodes",
                "7 nodes"
            ],
            "answerHash": "4b227777d4dd1fc61c6f884f48641d02b4d121d3fd328cb08b5531fcacdabf8a"
        },
        {
            "type": "true_false",
            "question": "In threshold signature schemes, the complete private key is temporarily reconstructed in memory during the signing process.",
            "options": [
                "True",
                "False"
            ],
            "answerHash": "fcbcf165908dd18a9e49f7ff27810176db8e9f63b4352213741664245224f8aa"
        },
        {
            "type": "multiple_choice",
            "question": "What is the primary purpose of Multi-Party Computation (MPC) in threshold signatures?",
            "options": [
                "To speed up the signing process",
                "To allow nodes to jointly compute signatures while keeping their key shares private",
                "To encrypt the final signature",
                "To reduce the number of nodes needed"
            ],
            "answerHash": "1c7f3c2c1e4c8c8e8f8d8c8e8f8d8c8e8f8d8c8e8f8d8c8e8f8d8c8e8f8d8c8e"
        },
        {
            "type": "fill_in_the_blank",
            "question": "A partial signature generated by a single node is ______ on its own and cannot be used to authorize anything.",
            "options": [
                "useless",
                "invalid",
                "incomplete",
                "temporary"
            ],
            "answerHash": "8f3c3c2c1e4c8c8e8f8d8c8e8f8d8c8e8f8d8c8e8f8d8c8e8f8d8c8e8f8d8c8e"
        },
        {
            "type": "multiple_choice",
            "question": "How does a threshold signature appear to external observers on the blockchain?",
            "options": [
                "As multiple signatures from different nodes",
                "As a special threshold signature format",
                "As one normal-looking signature indistinguishable from traditional signatures",
                "As an encrypted signature bundle"
            ],
            "answerHash": "d4735e3a265e16eee03f59718b9b5d03019c07d8b6c51f90da3a666eec13ab35"
        },
        {
            "type": "true_false",
            "question": "If an attacker steals one key share from a (5, 9) threshold system, they can forge signatures.",
            "options": [
                "True",
                "False"
            ],
            "answerHash": "fcbcf165908dd18a9e49f7ff27810176db8e9f63b4352213741664245224f8aa"
        }
    ]
}